clickhouse_rowbinary/__init__.py
clickhouse_rowbinary/__init__.pyi
clickhouse_rowbinary/_core.cpython-313-darwin.so
clickhouse_rowbinary/py.typed
clickhouse_rowbinary-0.4.0.dist-info/METADATA
clickhouse_rowbinary-0.4.0.dist-info/WHEEL
clickhouse_rowbinary-0.4.0.dist-info/licenses/LICENSE-APACHE
clickhouse_rowbinary-0.4.0.dist-info/licenses/LICENSE-MIT
clickhouse_rowbinary-0.4.0.dist-info/RECORD
