Metadata-Version: 2.4
Name: clickhouse-rowbinary
Version: 0.4.0
Classifier: Development Status :: 4 - Beta
Classifier: Intended Audience :: Developers
Classifier: License :: OSI Approved :: MIT License
Classifier: License :: OSI Approved :: Apache Software License
Classifier: Operating System :: OS Independent
Classifier: Programming Language :: Python :: 3
Classifier: Programming Language :: Python :: 3.12
Classifier: Programming Language :: Python :: 3.13
Classifier: Programming Language :: Python :: 3.14
Classifier: Programming Language :: Rust
Classifier: Topic :: Database
Classifier: Topic :: Software Development :: Libraries :: Python Modules
Classifier: Typing :: Typed
License-File: LICENSE-APACHE
License-File: LICENSE-MIT
Summary: Fast ClickHouse RowBinary format encoder/decoder
Keywords: clickhouse,rowbinary,database,encoding,decoding
License: MIT OR Apache-2.0
Requires-Python: >=3.12
Project-URL: Documentation, https://github.com/dovreshef/clickhouse-rowbinary#readme
Project-URL: Homepage, https://github.com/dovreshef/clickhouse-rowbinary
Project-URL: Repository, https://github.com/dovreshef/clickhouse-rowbinary
